ide_updater/__init__.py
ide_updater/config.py
ide_updater/main.py
ide_updater/modules/__init__.py
ide_updater/modules/base.py
ide_updater/modules/cursor.py
ide_updater/modules/kiro.py
ide_updater/modules/vscode.py
ide_updater-0.1.6.dist-info/METADATA
ide_updater-0.1.6.dist-info/WHEEL
ide_updater-0.1.6.dist-info/entry_points.txt
ide_updater-0.1.6.dist-info/licenses/LICENSE
ide_updater-0.1.6.dist-info/RECORD
