Metadata-Version: 2.4
Name: ide-updater
Version: 0.1.6
Summary: A powerful CLI tool for Linux developers to automatically update and manage popular IDEs (VS Code, Cursor) with smart version detection, progress tracking, and seamless installation handling
Project-URL: Homepage, https://github.com/cosmah/ide-updater
Project-URL: Repository, https://github.com/cosmah/ide-updater
Project-URL: Issues, https://github.com/cosmah/ide-updater/issues
Project-URL: Changelog, https://github.com/cosmah/ide-updater/blob/main/CHANGELOG.md
Project-URL: Documentation, https://github.com/cosmah/ide-updater#readme
Author-email: Cosmah <cosmahke4@gmail.com>
Maintainer-email: Cosmah <cosmahke4@gmail.com>
License: MIT
License-File: LICENSE
Keywords: appimage,automation,cli,cursor,developer-tools,development-environment,ide,kiro,linux,package-manager,tar-gz,updater,vscode
Classifier: Development Status :: 4 - Beta
Classifier: Environment :: Console
Classifier: Intended Audience :: Developers
Classifier: License :: OSI Approved :: MIT License
Classifier: Operating System :: POSIX :: Linux
Classifier: Programming Language :: Python :: 3
Classifier: Programming Language :: Python :: 3.8
Classifier: Programming Language :: Python :: 3.9
Classifier: Programming Language :: Python :: 3.10
Classifier: Programming Language :: Python :: 3.11
Classifier: Programming Language :: Python :: 3.12
Classifier: Topic :: Software Development
Classifier: Topic :: System :: Systems Administration
Classifier: Topic :: Utilities
Requires-Python: >=3.8
Requires-Dist: beautifulsoup4>=4.12.0
Requires-Dist: packaging>=23.2
Requires-Dist: requests>=2.31.0
Requires-Dist: rich>=13.0.0
Requires-Dist: typer>=0.9.0
Provides-Extra: dev
Requires-Dist: pytest-cov>=4.0.0; extra == 'dev'
Requires-Dist: pytest>=7.0.0; extra == 'dev'
